cheminventory/__init__.py
cheminventory/api.py
cheminventory/objects.py
cheminventory/utils.py
cheminventory-0.2.3.dist-info/DESCRIPTION.rst
cheminventory-0.2.3.dist-info/METADATA
cheminventory-0.2.3.dist-info/RECORD
cheminventory-0.2.3.dist-info/WHEEL
cheminventory-0.2.3.dist-info/metadata.json
cheminventory-0.2.3.dist-info/top_level.txt
tests/__init__.py
tests/test_sample.py
tutorial/__init__.py
